medium_multiply_CI_CD/__init__.py
medium_multiply_CI_CD/multiplication.py
medium_multiply_CI_CD-0.1.0.dist-info/METADATA
medium_multiply_CI_CD-0.1.0.dist-info/WHEEL
medium_multiply_CI_CD-0.1.0.dist-info/top_level.txt
medium_multiply_CI_CD-0.1.0.dist-info/RECORD
