Metadata-Version: 2.1
Name: medium-multiply-CI-CD
Version: 0.1.0
Summary: Demo library
Home-page: https://medium-multiply-CI-CD.readthedocs.io/
Author: Kolli
Author-email: satishkumar.kolli1992@gmail.com
License: ABC
Platform: UNKNOWN
Classifier: Intended Audience :: Developers
Classifier: License :: OSI Approved :: MIT License
Classifier: Programming Language :: Python
Classifier: Programming Language :: Python :: 3
Classifier: Programming Language :: Python :: 3.6
Classifier: Programming Language :: Python :: 3.7
Classifier: Programming Language :: Python :: 3.8
Classifier: Programming Language :: Python :: 3.9
Classifier: Operating System :: OS Independent
Requires-Dist: numpy
